AUTHORS.rst
CONTRIBUTING.rst
HISTORY.rst
LICENSE
MANIFEST.in
README.rst
setup.py
django_municipios.egg-info/PKG-INFO
django_municipios.egg-info/SOURCES.txt
django_municipios.egg-info/dependency_links.txt
django_municipios.egg-info/not-zip-safe
django_municipios.egg-info/top_level.txt
municipios/__init__.py
municipios/fields.py
municipios/forms.py
municipios/models.py
municipios/tests.py
municipios/urls.py
municipios/views.py
municipios/widgets.py
municipios/fixtures/dumpdata_uf_municipios_SEM_GEOM.tar.gz
municipios/fixtures/municipios.json.bz2
municipios/migrations/0001_initial.py
municipios/migrations/__init__.py
municipios/sql/create_table_municipio_20100717.sql
municipios/sql/create_table_uf_20100717.sql
municipios/sql/insert_spatial_ref_sys.sql
municipios/static/municipios/js/municipio.js
municipios/templates/municipios/municipio_field.html
municipios/templates/municipios/municipios_options.html
municipios/templates/municipios/teste.html
municipios/templates/municipios/uf_field.html
municipios/utils/__init__.py
municipios/utils/ibge.py
municipios/utils/settings.py