Metadata-Version: 1.1
Name: django-municipios
Version: 1.2.0
Summary: Aplicação plugável Django com modelos e widgets para os Municípios Brasileiros
Home-page: https://github.com/znc-sistemas/django-municipios
Author: ZNC Sistemas
Author-email: contato@znc.com.br
License: MIT
Keywords: django-municipios
Platform: UNKNOWN
Classifier: Framework :: Django
Classifier: Development Status :: 5 - Production/Stable
Classifier: Environment :: Web Environment
Classifier: Intended Audience :: Developers
Classifier: License :: OSI Approved :: MIT License
Classifier: Operating System :: OS Independent
Classifier: Programming Language :: Python
Classifier: Programming Language :: JavaScript
Classifier: Topic :: Utilities
Classifier: Natural Language :: Portuguese (Brazilian)
Classifier: Programming Language :: Python :: 3
Classifier: Programming Language :: Python :: 3.6
